gradco_c_routines.cpython-310-aarch64-linux-gnu.so
gradco.py
gradco-0.1.8.dist-info/LICENSE
gradco-0.1.8.dist-info/top_level.txt
gradco-0.1.8.dist-info/RECORD
gradco-0.1.8.dist-info/METADATA
gradco-0.1.8.dist-info/WHEEL
