Metadata-Version: 2.1
Name: gradco
Version: 0.1.8
Summary: GRaphlet-orbit ADjacency COunter (GRADCO).
Author-email: "Sam F. L. Windels" <sam.windels@bsc.es>
Maintainer-email: "Sam F. L. Windels" <sam.windels@bsc.es>
License: Attribution-NonCommercial-ShareAlike 4.0 International
Project-URL: source, https://github.com/samwindels/gradco
Keywords: graphlets,motifs,network analysis,graph,bioinformatics,systems biology
Requires-Python: >=3.10
License-File: LICENSE
Requires-Dist: scipy
Requires-Dist: numpy<2.0,>=1.26.0
